shapes2d/__init__.py
shapes2d/shapes_area.py
shapes2d-0.1.0.dist-info/METADATA
shapes2d-0.1.0.dist-info/WHEEL
shapes2d-0.1.0.dist-info/top_level.txt
shapes2d-0.1.0.dist-info/RECORD
