Metadata-Version: 2.4
Name: shapes2d
Version: 0.1.0
Summary: A Python package for calculating areas of 2D shapes
Author-email: GURUPRAKASH V K <developerguru03@gmail.com>
License: MIT
Keywords: geometry,math,area,shapes
Classifier: Programming Language :: Python :: 3
Classifier: License :: OSI Approved :: MIT License
Classifier: Operating System :: OS Independent
